aserto/authorizer/v2/__init__.py
aserto/authorizer/v2/api/__init__.py
aserto/authorizer/v2/api/decision_logs_pb2.py
aserto/authorizer/v2/api/decision_logs_pb2.pyi
aserto/authorizer/v2/api/decision_logs_pb2_grpc.py
aserto/authorizer/v2/api/decision_logs_pb2_grpc.pyi
aserto/authorizer/v2/api/identity_context_pb2.py
aserto/authorizer/v2/api/identity_context_pb2.pyi
aserto/authorizer/v2/api/identity_context_pb2_grpc.py
aserto/authorizer/v2/api/identity_context_pb2_grpc.pyi
aserto/authorizer/v2/api/module_pb2.py
aserto/authorizer/v2/api/module_pb2.pyi
aserto/authorizer/v2/api/module_pb2_grpc.py
aserto/authorizer/v2/api/module_pb2_grpc.pyi
aserto/authorizer/v2/api/policy_context_pb2.py
aserto/authorizer/v2/api/policy_context_pb2.pyi
aserto/authorizer/v2/api/policy_context_pb2_grpc.py
aserto/authorizer/v2/api/policy_context_pb2_grpc.pyi
aserto/authorizer/v2/api/policy_instance_pb2.py
aserto/authorizer/v2/api/policy_instance_pb2.pyi
aserto/authorizer/v2/api/policy_instance_pb2_grpc.py
aserto/authorizer/v2/api/policy_instance_pb2_grpc.pyi
aserto/authorizer/v2/authorizer_pb2.py
aserto/authorizer/v2/authorizer_pb2.pyi
aserto/authorizer/v2/authorizer_pb2_grpc.py
aserto/authorizer/v2/authorizer_pb2_grpc.pyi
google/api/annotations_pb2.py
google/api/annotations_pb2.pyi
google/api/annotations_pb2_grpc.py
google/api/annotations_pb2_grpc.pyi
google/api/http_pb2.py
google/api/http_pb2.pyi
google/api/http_pb2_grpc.py
google/api/http_pb2_grpc.pyi
protoc_gen_openapiv2/options/annotations_pb2.py
protoc_gen_openapiv2/options/annotations_pb2.pyi
protoc_gen_openapiv2/options/annotations_pb2_grpc.py
protoc_gen_openapiv2/options/annotations_pb2_grpc.pyi
protoc_gen_openapiv2/options/openapiv2_pb2.py
protoc_gen_openapiv2/options/openapiv2_pb2.pyi
protoc_gen_openapiv2/options/openapiv2_pb2_grpc.py
protoc_gen_openapiv2/options/openapiv2_pb2_grpc.pyi
aserto_authorizer-0.20.7.dist-info/LICENSE
aserto_authorizer-0.20.7.dist-info/METADATA
aserto_authorizer-0.20.7.dist-info/WHEEL
aserto_authorizer-0.20.7.dist-info/RECORD
