Metadata-Version: 2.3
Name: aserto_authorizer
Version: 0.20.7
Summary: gRPC client for Aserto Authorizer service instances
License: Apache-2.0
Author: Aserto, Inc.
Author-email: pypi@aserto.com
Requires-Python: >=3.9,<4
Classifier: Intended Audience :: Developers
Classifier: License :: OSI Approved :: Apache Software License
Classifier: Operating System :: OS Independent
Classifier: Programming Language :: Python
Classifier: Programming Language :: Python :: 3
Classifier: Programming Language :: Python :: 3.9
Classifier: Programming Language :: Python :: 3.10
Classifier: Programming Language :: Python :: 3.11
Classifier: Programming Language :: Python :: 3.12
Classifier: Programming Language :: Python :: 3.13
Classifier: Programming Language :: Python :: 3 :: Only
Classifier: Topic :: Software Development :: Libraries
Classifier: Typing :: Typed
Requires-Dist: grpcio (>=1.71.0,<2.0.0)
Requires-Dist: protobuf (>=6.30.1,<7.0.0)
Requires-Dist: types-protobuf (>=5.29,<6.0)
Project-URL: Documentation, https://github.com/aserto-dev/python-authorizer
Project-URL: Homepage, https://github.com/aserto-dev/python-authorizer
Project-URL: Repository, https://github.com/aserto-dev/python-authorizer
